hoangecg/__init__.py
hoangecg/chrworks.py
hoangecg/resolume.py
hoangecg/tc1.py
hoangecg/vmix.py
hoangecg-0.1.2.dist-info/METADATA
hoangecg-0.1.2.dist-info/WHEEL
hoangecg-0.1.2.dist-info/top_level.txt
hoangecg-0.1.2.dist-info/RECORD
