Metadata-Version: 2.2
Name: hoangecg
Version: 0.1.2
Summary: Module remote vMix, Resolume, Chrworks, TC1
Home-page: https://github.com/HoangECG
Author: hoangecg
Author-email: hoangecg@gmail.com
Classifier: Programming Language :: Python :: 3
Classifier: License :: OSI Approved :: MIT License
Classifier: Operating System :: OS Independent
Requires-Python: >=3.6
Requires-Dist: requests
Dynamic: author
Dynamic: author-email
Dynamic: classifier
Dynamic: description
Dynamic: description-content-type
Dynamic: home-page
Dynamic: requires-dist
Dynamic: requires-python
Dynamic: summary
